tcripser.cpython-312-x86_64-linux-musl.so
cripser/utils.py
cripser/_cripser.cpython-312-x86_64-linux-musl.so
cripser/__init__.py
cripser-0.0.21.dist-info/RECORD
cripser-0.0.21.dist-info/METADATA
cripser-0.0.21.dist-info/top_level.txt
cripser-0.0.21.dist-info/WHEEL
cripser-0.0.21.dist-info/licenses/LICENSE
cripser.libs/libgcc_s-a04fdf82.so.1
cripser.libs/libstdc++-a9383cce.so.6.0.28
