Metadata-Version: 2.1
Name: cripser
Version: 0.0.21
Summary: Cubical Ripser Python binding
Author-email: Shizuo Kaji <shizuo.kaji@gmail.com>
License: GNU GENERAL PUBLIC LICENSE
Project-URL: Homepage, https://github.com/shizuo-kaji/CubicalRipser_3dim
Keywords: persistent homology,TDA,cubical complex,image,volume
Requires-Python: >=3.8
License-File: LICENSE
